torch_uncertainty_assets/__init__.py
torch_uncertainty_assets/frost/__init__.py
torch_uncertainty_assets/frost/frost1.jpg
torch_uncertainty_assets/frost/frost2.jpg
torch_uncertainty_assets/frost/frost3.jpg
torch_uncertainty_assets/frost/frost4.jpg
torch_uncertainty_assets/frost/frost5.jpg
torch_uncertainty_assets-0.5.2.dist-info/licenses/LICENSE
torch_uncertainty_assets-0.5.2.dist-info/WHEEL
torch_uncertainty_assets-0.5.2.dist-info/METADATA
torch_uncertainty_assets-0.5.2.dist-info/RECORD
