Metadata-Version: 2.4
Name: torch-uncertainty-assets
Version: 0.5.2
Summary: Uncertainty quantification library in PyTorch
Keywords: bayesian-network,ensembles,neural-networks,predictive-uncertainty,reliable-ai,trustworthy-machine-learning,uncertainty,uncertainty-quantification
Author-email: ENSTA U2IS <olivier.laurent@ensta.fr>, Adrien Lafage <adrienlafage@outlook.com>, Olivier Laurent <olivier.laurent@ensta.fr>
Requires-Python: >=3.10
Classifier: License :: OSI Approved :: Apache Software License
Classifier: Programming Language :: Python :: 3 :: Only
Classifier: Programming Language :: Python :: 3.10
Classifier: Programming Language :: Python :: 3.11
Classifier: Programming Language :: Python :: 3.12
Classifier: Programming Language :: Python :: 3.13
License-File: LICENSE
Project-URL: documentation, https://torch-uncertainty.github.io/quickstart.html
Project-URL: homepage, https://torch-uncertainty.github.io/
Project-URL: repository, https://github.com/torch-uncertainty/torch-uncertainty-assets
